<C0010>
	<DocID>RN001</DocID>
	<CreateTime>20201203140023</CreateTime>
	<DocSetID>RN001-10</DocSetID>
	<Version>1.0</Version>
	<RecordTime>20201201</RecordTime>
	<AuthorCode>0030</AuthorCode>
	<AuthorName>李雷</AuthorName>
	<CustodianOrgCode>JG001</CustodianOrgCode>
	<CustodianOrgName>阆中市人民医院</CustodianOrgName>
	<OutPatientID>E2020120100001</OutPatientID>
	<HospitalizationID>2012000005</HospitalizationID>
	<ApplyID>SQ2012010000010</ApplyID>
	<PatientInfo>
		<IDCardNo>420106201101011919</IDCardNo>
		<PatientName>贾小明</PatientName>
		<GenderCode>1</GenderCode>
		<GenderName>男性</GenderName>
		<BirthTime></BirthTime>
		<PatientAge>9</PatientAge>
	</PatientInfo>
	<AnesthesiaInfoSignInfo>
		<row>
			<Time>202012011600</Time>
			<Code>0031</Code>
			<Name>韩梅梅</Name>
		</row>
		<row>
			<Time>202012011659</Time>
			<Code>0032</Code>
			<Name>王林</Name>
		</row>
	</AnesthesiaInfoSignInfo>
	<HospitalizationTime>20201201103011</HospitalizationTime>
	<BedCode>001</BedCode>
	<BedName>1床</BedName>
	<RoomCode>002</RoomCode>
	<RoomName>205室</RoomName>
	<DeptCode>KS001</DeptCode>
	<DeptName>儿科住院部</DeptName>
	<AreaCode>010</AreaCode>
	<AreaName>儿科住院部一病区</AreaName>
	<OrganCode>JG001</OrganCode>
	<OrganName>阆中市人民医院</OrganName>
	<PreoperativeDiagCode>J01.9</PreoperativeDiagCode>
	<PreoperativeDiagName>上呼吸道疾病NOS</PreoperativeDiagName>
	<PreoperativeComorbidities>副鼻窦炎</PreoperativeComorbidities>
	<BriefIllnessDesc>头晕眼花，鼻塞，手脚颤抖</BriefIllnessDesc>
	<AllergiesDesc>
		<AllergiesDescItem>粉尘</AllergiesDescItem>
		<AllergiesDescItem>青霉素</AllergiesDescItem>
	</AllergiesDesc>
	<PatientWeight>39.23</PatientWeight>
	<GeneralExamResult>
		<GeneralExamResultItem>面部神态正常</GeneralExamResultItem>
		<GeneralExamResultItem>体态正常</GeneralExamResultItem>
		<GeneralExamResultItem>听力正常</GeneralExamResultItem>
		<GeneralExamResultItem>意识清晰</GeneralExamResultItem>
	</GeneralExamResult>
	<MentalStateSign>false</MentalStateSign>
	<HeartAuscultationResult>心率：70次/分吸。气时心率增快，呼气时减慢。无杂音</HeartAuscultationResult>
	<LungsAuscultationResult>双肺呼吸音清</LungsAuscultationResult>
	<LimbsExamResult>四肢活动正常</LimbsExamResult>
	<SpineExamResult>脊柱正常</SpineExamResult>
	<AbdominalExamResult>腹部正常</AbdominalExamResult>
	<TracheaExamResult>气管正常</TracheaExamResult>
	<TeethExamResult>牙齿正常，无龋齿等情况</TeethExamResult>
	<ABOBloodTypeCode>2</ABOBloodTypeCode>
	<ABOBloodTypeName>B型</ABOBloodTypeName>
	<RHBloodTypeCode>2</RHBloodTypeCode>
	<RHBloodTypeName>Rh阴性</RHBloodTypeName>
	<ECGExamResult>心电图正常</ECGExamResult>
	<ChestXRayExamResult>胸部X线检查无异常</ChestXRayExamResult>
	<CTExamResult>CT检查无异常</CTExamResult>
	<BScanExamResult>B超检查无异常</BScanExamResult>
	<MRIExamResult>MRT检查无异常</MRIExamResult>
	<LungFunctionExamResult>肺功能检查无异常</LungFunctionExamResult>
	<BloodRoutineExamResult>血常规检查无异常</BloodRoutineExamResult>
	<UrineRoutineExamResult>尿常规检查无异常</UrineRoutineExamResult>
	<BloodCoagulationExamResult>凝血功能检查无异常</BloodCoagulationExamResult>
	<LiverFunctionExamCode>2</LiverFunctionExamCode>
	<BloodGasExamResult>血气分析检查无异常</BloodGasExamResult>
	<AnticipatedOperationInfo>
		<row>
			<AnticipatedOperationCode>44.66</AnticipatedOperationCode>
			<AnticipatedOperationName>胃底折叠术(食管)</AnticipatedOperationName>
			<OperationRoomCode>010</OperationRoomCode>
		</row>
		<row>
			<AnticipatedOperationCode>48.36</AnticipatedOperationCode>
			<AnticipatedOperationName>内镜下直肠息肉切除术</AnticipatedOperationName>
			<OperationRoomCode>010</OperationRoomCode>
		</row>
	</AnticipatedOperationInfo>
	<AnticipatedAnesthesiaInfo>
		<row>
			<AnticipatedAnesthesiaMethodCode>13</AnticipatedAnesthesiaMethodCode>
			<AnticipatedAnesthesiaMethodName>基础麻醉</AnticipatedAnesthesiaMethodName>
			<AnesthesiaOrderDesc>利多卡因，注射，3mg</AnesthesiaOrderDesc>
			<AnesthesiaIndicationDesc>无</AnesthesiaIndicationDesc>
			<AnesthesiaNote>若出现异常，应及时停止注射并注意观察患者情况</AnesthesiaNote>
		</row>
		<row>
			<AnticipatedAnesthesiaMethodCode>1</AnticipatedAnesthesiaMethodCode>
			<AnticipatedAnesthesiaMethodName>全身麻醉</AnticipatedAnesthesiaMethodName>
			<AnesthesiaOrderDesc>利多卡因，注射，3mg</AnesthesiaOrderDesc>
			<AnesthesiaIndicationDesc>无</AnesthesiaIndicationDesc>
			<AnesthesiaNote>若出现异常，应及时停止注射并注意观察患者情况</AnesthesiaNote>
		</row>
	</AnticipatedAnesthesiaInfo>
</C0010>
